{"departamentos":[{"centroide":{"lat":-32.6006392247111,"lon":-66.1273702635842},"id":"74007","nombre":"Ayacucho"},{"centroide":{"lat":-34.7582787968944,"lon":-65.2503691694475},"id":"74042","nombre":"Gobernador Dupuy"},{"centroide":{"lat":-32.6661925630758,"lon":-66.4524010178082},"id":"74014","nombre":"Belgrano"},{"centroide":{"lat":-32.3423081509941,"lon":-65.2071206614116},"id":"74049","nombre":"Junín"},{"centroide":{"lat":-32.5607275180287,"lon":-65.2452806076649},"id":"74028","nombre":"Chacabuco"},{"centroide":{"lat":-33.3023139659883,"lon":-66.3360877357358},"id":"74056","nombre":"Juan Martín de Pueyrredón"},{"centroide":{"lat":-33.6738636408858,"lon":-65.4624765290195},"id":"74035","nombre":"General Pedernera"},{"centroide":{"lat":-32.4132690463753,"lon":-65.6759306690121},"id":"74063","nombre":"Libertador General San Martín"},{"centroide":{"lat":-33.0544376204479,"lon":-65.62269821015},"id":"74021","nombre":"Coronel Pringles"}],"cantidad":9}